MANIFEST.in
README.rst
setup.py
emp_offline/__init__.py
emp_offline/ide.py
emp_offline.egg-info/PKG-INFO
emp_offline.egg-info/SOURCES.txt
emp_offline.egg-info/dependency_links.txt
emp_offline.egg-info/entry_points.txt
emp_offline.egg-info/requires.txt
emp_offline.egg-info/top_level.txt
emp_offline/static/css.worker.js
emp_offline/static/css.worker.js.map
emp_offline/static/editor.worker.js
emp_offline/static/editor.worker.js.map
emp_offline/static/favicon.ico
emp_offline/static/html.worker.js
emp_offline/static/html.worker.js.map
emp_offline/static/index.html
emp_offline/static/json.worker.js
emp_offline/static/json.worker.js.map
emp_offline/static/typescript.worker.js
emp_offline/static/typescript.worker.js.map
emp_offline/static/css/app.39efe745.css
emp_offline/static/css/chunk-0647d7dc.0b9dbeff.css
emp_offline/static/css/chunk-105ecf8e.94d8ee91.css
emp_offline/static/css/chunk-152aa660.e5ff0d51.css
emp_offline/static/css/chunk-2ac974e4.9fcb523d.css
emp_offline/static/css/chunk-324a8daa.42c093fa.css
emp_offline/static/css/chunk-3ef5cf24.7df6edf9.css
emp_offline/static/css/chunk-5343f65a.42c093fa.css
emp_offline/static/css/chunk-5cf56edd.1ab62ebb.css
emp_offline/static/css/chunk-5f5b5007.7feb5007.css
emp_offline/static/css/chunk-6146d972.d06980e6.css
emp_offline/static/css/chunk-66551290.0b9dbeff.css
emp_offline/static/css/chunk-6f24c2c8.fcc41532.css
emp_offline/static/css/chunk-6f2a5820.d06980e6.css
emp_offline/static/css/chunk-707eb013.1ab62ebb.css
emp_offline/static/css/chunk-a6604a3e.91ac850b.css
emp_offline/static/css/chunk-ab01839c.fcc41532.css
emp_offline/static/css/chunk-abafcd8e.91ac850b.css
emp_offline/static/css/chunk-b441fb64.25d54002.css
emp_offline/static/css/chunk-ba7886f2.b43f01ff.css
emp_offline/static/css/chunk-cb1baf7a.7feb5007.css
emp_offline/static/css/chunk-cbe61776.7ccac7b3.css
emp_offline/static/css/chunk-d8fb7f32.6d04e539.css
emp_offline/static/css/chunk-e6edb01a.701f32e3.css
emp_offline/static/css/chunk-fedbce3e.701f32e3.css
emp_offline/static/css/chunk-vendors.2f883a2c.css
emp_offline/static/fonts/MaterialIcons-Regular.012cf6a1.woff
emp_offline/static/fonts/MaterialIcons-Regular.570eb838.woff2
